README
setup.py
k2pix/__init__.py
k2pix/figure.py
k2pix/main.py
k2pix/surveyquery.py
k2pix/tpf.py
k2pix.egg-info/PKG-INFO
k2pix.egg-info/SOURCES.txt
k2pix.egg-info/dependency_links.txt
k2pix.egg-info/entry_points.txt
k2pix.egg-info/requires.txt
k2pix.egg-info/top_level.txt