Metadata-Version: 1.1
Name: k2pix
Version: 0.1
Summary: Overlaying a Sky View survey image's contours onto a K2 pixel stamp
Home-page: https://github.com/gully/k2-pix
Author: Stephanie Douglas and GitHub contributors
Author-email: UNKNOWN
License: MIT
Keywords: astronomy astrophysics
Platform: UNKNOWN
Classifier: Development Status :: 3 - Alpha
Classifier: Intended Audience :: Science/Research
Classifier: License :: OSI Approved :: MIT License
Classifier: Programming Language :: Python :: 3.6
